tts_webui_extension/mimo_audio/__init__.py
tts_webui_extension/mimo_audio/main.py
tts_webui_extension/mimo_audio/run_mimo_audio.py
tts_webui_extension_mimo_audio-0.0.5.dist-info/licenses/LICENSE
tts_webui_extension_mimo_audio-0.0.5.dist-info/METADATA
tts_webui_extension_mimo_audio-0.0.5.dist-info/WHEEL
tts_webui_extension_mimo_audio-0.0.5.dist-info/top_level.txt
tts_webui_extension_mimo_audio-0.0.5.dist-info/RECORD
