Metadata-Version: 2.4
Name: tts_webui_extension.mimo_audio
Version: 0.0.5
Summary: A template extension for TTS Generation WebUI
Home-page: https://github.com/rsxdalv/tts_webui_extension.mimo_audio
Author: rsxdalv
Classifier: Programming Language :: Python :: 3
Classifier: License :: OSI Approved :: MIT License
Classifier: Operating System :: OS Independent
License-File: LICENSE
Requires-Dist: tts-webui.mimo-audio>=0.0.3
Dynamic: author
Dynamic: classifier
Dynamic: description
Dynamic: description-content-type
Dynamic: home-page
Dynamic: license-file
Dynamic: requires-dist
Dynamic: summary
